nyxara-0.2.0.dist-info/METADATA
nyxara-0.2.0.dist-info/WHEEL
nyxara-0.2.0.dist-info/entry_points.txt
nyxara-0.2.0.dist-info/licenses/LICENSE
nyxara/__init__.py
nyxara-0.2.0.dist-info/RECORD
