Metadata-Version: 2.1
Name: nyxara
Version: 0.2.0
Summary: nyxara
Author: nyxara
License: MIT
Requires-Python: >=3.13
